barpy
