Metadata-Version: 1.1
Name: barpy
Version: 0.1.1
Summary: Ruby barby barcodes generating library port to Python
Home-page: http://github.com/kstep/barpy/
Author: Konstantin Stepanov
Author-email: me@kstep.me
License: BSD
Platform: UNKNOWN
Classifier: Development Status :: 3 - Alpha
Classifier: License :: OSI Approved :: BSD License
Classifier: Operating System :: POSIX
Classifier: Programming Language :: Python :: 2.7
Classifier: Topic :: Software Development :: Libraries
